grana/__init__.py
grana/actions/__init__.py
grana/actions/base.py
grana/actions/bundled/__init__.py
grana/actions/bundled/docker_shell.py
grana/actions/bundled/echo.py
grana/actions/bundled/shell.py
grana/actions/bundled/subflow.py
grana/actions/constants.py
grana/actions/types.py
grana/config/__init__.py
grana/config/constants/__init__.py
grana/config/constants/cli.py
grana/config/constants/helpers.py
grana/config/environment.py
grana/console.py
grana/display/__init__.py
grana/display/base.py
grana/display/color.py
grana/display/default.py
grana/display/types.py
grana/display/utils.py
grana/exceptions.py
grana/loader/__init__.py
grana/loader/base.py
grana/loader/default.py
grana/loader/helpers.py
grana/py.typed
grana/rendering/__init__.py
grana/rendering/constants.py
grana/rendering/containers.py
grana/rendering/tokenizing.py
grana/runner.py
grana/strategy.py
grana/tools/__init__.py
grana/tools/concealment.py
grana/tools/inspect.py
grana/tools/proxy.py
grana/types.py
grana/version.py
grana/workflow.py
grana-1.3.0.dist-info/LICENSE
grana-1.3.0.dist-info/METADATA
grana-1.3.0.dist-info/WHEEL
grana-1.3.0.dist-info/entry_points.txt
grana-1.3.0.dist-info/RECORD
