Metadata-Version: 2.1
Name: grana
Version: 1.3.0
Summary: Declarative task runner
Home-page: https://github.com/reartnew/grana
License: MIT
Author: Artem Novikov
Author-email: artnew@list.ru
Requires-Python: >=3.9,<3.14
Classifier: Development Status :: 5 - Production/Stable
Classifier: License :: OSI Approved :: MIT License
Classifier: Programming Language :: Python :: 3
Classifier: Programming Language :: Python :: 3.9
Classifier: Programming Language :: Python :: 3.10
Classifier: Programming Language :: Python :: 3.11
Classifier: Programming Language :: Python :: 3.12
Classifier: Programming Language :: Python :: 3.13
Classifier: Typing :: Typed
Provides-Extra: all
Provides-Extra: docker
Provides-Extra: tests
Requires-Dist: aiodocker (>=0.24.0,<0.25.0) ; extra == "docker" or extra == "all"
Requires-Dist: async-shell (>=1.1.0,<2.0.0)
Requires-Dist: bandit (>=1.7.9,<2.0.0) ; extra == "tests"
Requires-Dist: black (>=24.8.0,<25.0.0) ; extra == "tests"
Requires-Dist: classlogging (>=1.2.1,<2.0.0)
Requires-Dist: click (>=8.1.8,<9.0.0)
Requires-Dist: coverage (>=7.6.1,<8.0.0) ; extra == "tests"
Requires-Dist: dacite-cjunct (==1.8.1a0)
Requires-Dist: inquirer (>=3.4.0,<4.0.0)
Requires-Dist: lazy-object-proxy (>=1.10.0,<2.0.0)
Requires-Dist: mypy (>=1.11.1,<2.0.0) ; extra == "tests"
Requires-Dist: named-env (>=2.4.1,<3.0.0)
Requires-Dist: pylint (>=3.2.6,<4.0.0) ; extra == "tests"
Requires-Dist: pytest (>=8.3.2,<9.0.0) ; extra == "tests"
Requires-Dist: pytest-asyncio (>=0.25.1,<0.26.0) ; extra == "tests"
Requires-Dist: pytest-bandit (>=0.6.1,<0.7.0) ; extra == "tests"
Requires-Dist: pytest-black (>=0.6.0,<0.7.0) ; extra == "tests"
Requires-Dist: pytest-cov (>=6.0.0,<7.0.0) ; extra == "tests"
Requires-Dist: pytest-data-suites (>=1.0.5,<2.0.0) ; extra == "tests"
Requires-Dist: pytest-mypy (>=0.10.3,<0.11.0) ; extra == "tests"
Requires-Dist: pytest-pylint (>=0.21.0,<0.22.0) ; extra == "tests"
Requires-Dist: python-dotenv (>=1.0.1,<2.0.0)
Requires-Dist: pyyaml (>=6.0.2,<7.0.0)
Requires-Dist: types-pyyaml (>=6.0.12.20240311,<7.0.0.0) ; extra == "tests"
Project-URL: Repository, https://github.com/reartnew/grana
